{"_ts":[1562777227,1562817380,1562861016,1562905167,1562951833],"_r":{"breakdown":{"html":{"bytes":[34300,34011,33986,34396,34005],"requests":[6,7,7,6,6]},"js":{"bytes":[1009383,1009360,1010643,1010649,1010513],"requests":[28,28,28,28,28]},"css":{"bytes":[54642,54642,55173,55173,55173],"requests":[3,3,3,3,3]},"image":{"bytes":[601270,601270,601270,601270,601270],"requests":[45,45,45,45,45]},"flash":{"bytes":[0,0,0,0,0],"requests":[0,0,0,0,0]},"font":{"bytes":[113264,113264,113264,113264,113264],"requests":[7,7,7,7,7]},"video":{"bytes":[0,0,0,0,0],"requests":[0,0,0,0,0]},"other":{"bytes":[524,524,524,524,524],"requests":[4,4,4,4,4]}},"date":[1562777227,1562817380,1562861016,1562905167,1562951833],"domElements":[867,867,867,867,869],"domInteractive":[2925,3033,2856,3131,2878],"firstPaint":[850.3500000006,901.464999999,861.8900000001,950.1500000006,873.695000002],"fullyLoaded":[5417,4975,4786,4932,4928],"id":["190710_W4_1f427a392f0fe6fff7fb6c758c3d5306","190711_RH_f563facd9db6fc6f03b808c57d5d2a58","190711_3Q_972877dd86b24173ff3e0f99442a9ddf","190712_89_25576fcbc54c9d92b960010e8e8226de","190712_MA_9d855dad63a630e61cd7046e2b6bc99f"],"loadTime":[4207,3457,3288,3514,3704],"render":[800,900,900,900,800],"SpeedIndex":[1209,1900,1829,1841,1615],"TTFB":[345,428,360,371,386],"videoFrames":[[{"_i":"ms_000000.jpg","_t":0,"_vc":0},{"_i":"ms_000800.jpg","_t":800,"_vc":28},{"_i":"ms_000900.jpg","_t":900,"_vc":28},{"_i":"ms_001200.jpg","_t":1200,"_vc":94},{"_i":"ms_001300.jpg","_t":1300,"_vc":94},{"_i":"ms_001400.jpg","_t":1400,"_vc":94},{"_i":"ms_003000.jpg","_t":3000,"_vc":99},{"_i":"ms_003300.jpg","_t":3300,"_vc":98},{"_i":"ms_003400.jpg","_t":3400,"_vc":99},{"_i":"ms_003500.jpg","_t":3500,"_vc":99},{"_i":"ms_004000.jpg","_t":4000,"_vc":99},{"_i":"ms_004200.jpg","_t":4200,"_vc":100}],[{"_i":"ms_000000.jpg","_t":0,"_vc":0},{"_i":"ms_000900.jpg","_t":900,"_vc":28},{"_i":"ms_001500.jpg","_t":1500,"_vc":28},{"_i":"ms_001600.jpg","_t":1600,"_vc":28},{"_i":"ms_002200.jpg","_t":2200,"_vc":94},{"_i":"ms_003100.jpg","_t":3100,"_vc":99},{"_i":"ms_003300.jpg","_t":3300,"_vc":99},{"_i":"ms_003600.jpg","_t":3600,"_vc":96},{"_i":"ms_003700.jpg","_t":3700,"_vc":99},{"_i":"ms_003800.jpg","_t":3800,"_vc":100}],[{"_i":"ms_000000.jpg","_t":0,"_vc":0},{"_i":"ms_000900.jpg","_t":900,"_vc":28},{"_i":"ms_001000.jpg","_t":1000,"_vc":28},{"_i":"ms_001300.jpg","_t":1300,"_vc":28},{"_i":"ms_001400.jpg","_t":1400,"_vc":28},{"_i":"ms_001500.jpg","_t":1500,"_vc":28},{"_i":"ms_002100.jpg","_t":2100,"_vc":94},{"_i":"ms_003000.jpg","_t":3000,"_vc":99},{"_i":"ms_003100.jpg","_t":3100,"_vc":99},{"_i":"ms_003200.jpg","_t":3200,"_vc":99},{"_i":"ms_003500.jpg","_t":3500,"_vc":97},{"_i":"ms_003600.jpg","_t":3600,"_vc":97},{"_i":"ms_003700.jpg","_t":3700,"_vc":100}],[{"_i":"ms_000000.jpg","_t":0,"_vc":0},{"_i":"ms_000900.jpg","_t":900,"_vc":28},{"_i":"ms_001000.jpg","_t":1000,"_vc":28},{"_i":"ms_001300.jpg","_t":1300,"_vc":28},{"_i":"ms_001500.jpg","_t":1500,"_vc":28},{"_i":"ms_001600.jpg","_t":1600,"_vc":28},{"_i":"ms_002100.jpg","_t":2100,"_vc":94},{"_i":"ms_003200.jpg","_t":3200,"_vc":99},{"_i":"ms_003300.jpg","_t":3300,"_vc":99},{"_i":"ms_003400.jpg","_t":3400,"_vc":99},{"_i":"ms_003600.jpg","_t":3600,"_vc":96},{"_i":"ms_003700.jpg","_t":3700,"_vc":97},{"_i":"ms_003800.jpg","_t":3800,"_vc":100}],[{"_i":"ms_000000.jpg","_t":0,"_vc":0},{"_i":"ms_000800.jpg","_t":800,"_vc":11},{"_i":"ms_000900.jpg","_t":900,"_vc":28},{"_i":"ms_001200.jpg","_t":1200,"_vc":28},{"_i":"ms_001300.jpg","_t":1300,"_vc":28},{"_i":"ms_001400.jpg","_t":1400,"_vc":27},{"_i":"ms_001800.jpg","_t":1800,"_vc":94},{"_i":"ms_002000.jpg","_t":2000,"_vc":94},{"_i":"ms_002900.jpg","_t":2900,"_vc":99},{"_i":"ms_003000.jpg","_t":3000,"_vc":99},{"_i":"ms_003200.jpg","_t":3200,"_vc":99},{"_i":"ms_003400.jpg","_t":3400,"_vc":99},{"_i":"ms_003500.jpg","_t":3500,"_vc":99},{"_i":"ms_003600.jpg","_t":3600,"_vc":99},{"_i":"ms_003700.jpg","_t":3700,"_vc":100}]],"visualComplete":[4200,3800,3700,3800,3700],"lighthouse":[27,27,27,27,27],"pagespeed":[79,79,80,80,80]}}