{"_ts":[1567343772,1567388960,1567432732,1567476971],"_r":{"breakdown":{"html":{"bytes":[34067,33555,34110,34225],"requests":[8,8,8,9]},"js":{"bytes":[1482038,1482044,1482143,1482104],"requests":[39,39,39,39]},"css":{"bytes":[50495,50495,50495,50495],"requests":[5,5,5,5]},"image":{"bytes":[735681,735681,735681,735681],"requests":[43,43,43,43]},"flash":{"bytes":[0,0,0,0],"requests":[0,0,0,0]},"font":{"bytes":[129444,129444,129444,129444],"requests":[8,8,8,8]},"video":{"bytes":[0,0,0,0],"requests":[0,0,0,0]},"other":{"bytes":[11977,12043,11977,12043],"requests":[6,6,6,6]}},"date":[1567343772,1567388960,1567432732,1567476971],"domElements":[1169,1169,1169,1169],"domInteractive":[3835,3209,3330,3981],"firstPaint":[1217.5450000068,644.9500000017,726.1200000066,1477.5000000009],"fullyLoaded":[8057,7243,7817,8001],"id":["190901_Q2_b446a9fda4ebf7559f04986b89f484b2","190902_26_f733d527bbf5705218dd7ff16c1ddc80","190902_4C_0fafe0e350f0d9a6a4802ae10a8d009e","190903_Q5_fabbf132e81aa4376031be88352d2bb0"],"loadTime":[5643,5021,5578,5692],"render":[1300,700,800,1500],"SpeedIndex":[2199,1704,1452,2363],"TTFB":[780,235,276,1027],"videoFrames":[[{"_i":"ms_000000.jpg","_t":0,"_vc":0},{"_i":"ms_001300.jpg","_t":1300,"_vc":46},{"_i":"ms_001600.jpg","_t":1600,"_vc":46},{"_i":"ms_001700.jpg","_t":1700,"_vc":46},{"_i":"ms_001800.jpg","_t":1800,"_vc":46},{"_i":"ms_001900.jpg","_t":1900,"_vc":49},{"_i":"ms_002500.jpg","_t":2500,"_vc":49},{"_i":"ms_002900.jpg","_t":2900,"_vc":92},{"_i":"ms_003300.jpg","_t":3300,"_vc":96},{"_i":"ms_003800.jpg","_t":3800,"_vc":98},{"_i":"ms_003900.jpg","_t":3900,"_vc":98},{"_i":"ms_004000.jpg","_t":4000,"_vc":98},{"_i":"ms_004300.jpg","_t":4300,"_vc":99},{"_i":"ms_004500.jpg","_t":4500,"_vc":100},{"_i":"ms_004600.jpg","_t":4600,"_vc":100},{"_i":"ms_004700.jpg","_t":4700,"_vc":99},{"_i":"ms_004800.jpg","_t":4800,"_vc":100}],[{"_i":"ms_000000.jpg","_t":0,"_vc":0},{"_i":"ms_000700.jpg","_t":700,"_vc":46},{"_i":"ms_000900.jpg","_t":900,"_vc":46},{"_i":"ms_001000.jpg","_t":1000,"_vc":46},{"_i":"ms_001400.jpg","_t":1400,"_vc":46},{"_i":"ms_002400.jpg","_t":2400,"_vc":89},{"_i":"ms_003000.jpg","_t":3000,"_vc":96},{"_i":"ms_003200.jpg","_t":3200,"_vc":98},{"_i":"ms_003300.jpg","_t":3300,"_vc":98},{"_i":"ms_003600.jpg","_t":3600,"_vc":98},{"_i":"ms_003700.jpg","_t":3700,"_vc":99},{"_i":"ms_003900.jpg","_t":3900,"_vc":100},{"_i":"ms_004000.jpg","_t":4000,"_vc":100},{"_i":"ms_004100.jpg","_t":4100,"_vc":100}],[{"_i":"ms_000000.jpg","_t":0,"_vc":0},{"_i":"ms_000800.jpg","_t":800,"_vc":46},{"_i":"ms_001100.jpg","_t":1100,"_vc":49},{"_i":"ms_001200.jpg","_t":1200,"_vc":49},{"_i":"ms_001900.jpg","_t":1900,"_vc":96},{"_i":"ms_002000.jpg","_t":2000,"_vc":96},{"_i":"ms_003300.jpg","_t":3300,"_vc":97},{"_i":"ms_003400.jpg","_t":3400,"_vc":97},{"_i":"ms_003500.jpg","_t":3500,"_vc":98},{"_i":"ms_003900.jpg","_t":3900,"_vc":98},{"_i":"ms_004000.jpg","_t":4000,"_vc":98},{"_i":"ms_004500.jpg","_t":4500,"_vc":100}],[{"_i":"ms_000000.jpg","_t":0,"_vc":0},{"_i":"ms_001500.jpg","_t":1500,"_vc":46},{"_i":"ms_001600.jpg","_t":1600,"_vc":46},{"_i":"ms_001900.jpg","_t":1900,"_vc":46},{"_i":"ms_002000.jpg","_t":2000,"_vc":46},{"_i":"ms_002100.jpg","_t":2100,"_vc":46},{"_i":"ms_002200.jpg","_t":2200,"_vc":46},{"_i":"ms_003000.jpg","_t":3000,"_vc":96},{"_i":"ms_003500.jpg","_t":3500,"_vc":96},{"_i":"ms_004000.jpg","_t":4000,"_vc":98},{"_i":"ms_004100.jpg","_t":4100,"_vc":98},{"_i":"ms_004500.jpg","_t":4500,"_vc":99},{"_i":"ms_004700.jpg","_t":4700,"_vc":99},{"_i":"ms_004800.jpg","_t":4800,"_vc":100}]],"visualComplete":[4500,3900,4500,4800],"lighthouse":[27,27,27,27],"pagespeed":[78,77,78,79]}}